airflow/__init__.py
airflow/www/static/logo.png
airflow/www/templates/appbuilder/navbar.html
airflow/www/templates/appbuilder/navbar_right.html
dataflow_airflow_testing2-2.10.5.dist-info/METADATA
dataflow_airflow_testing2-2.10.5.dist-info/WHEEL
dataflow_airflow_testing2-2.10.5.dist-info/top_level.txt
dataflow_airflow_testing2-2.10.5.dist-info/RECORD
